baeuda/__init__.py
baeuda/run.py
baeuda/run_new.py
baeuda/settings.py
baeuda/test_settings.py
baeuda/datasource/__init__.py
baeuda/datasource/mdfile.py
baeuda-0.5.0.dist-info/LICENSE
baeuda-0.5.0.dist-info/METADATA
baeuda-0.5.0.dist-info/WHEEL
baeuda-0.5.0.dist-info/top_level.txt
baeuda-0.5.0.dist-info/RECORD
