Metadata-Version: 2.1
Name: baeuda
Version: 0.5.0
Summary: ":mortar_board: Baeuda - 배우다 - Learn - Create Anki Cards from various datasources"
Home-page: https://github.com/foxmask/baeuda
Author: 폭스마스크
Author-email: foxmask+git@pm.me
License: WTFPL
Keywords: anki card markdown
Classifier: Development Status :: 4 - Beta
Classifier: Environment :: Web Environment
Classifier: Intended Audience :: Developers
Classifier: License :: Public Domain
Classifier: Operating System :: OS Independent
Classifier: Programming Language :: Python
Classifier: Programming Language :: Python :: 3.10
Classifier: Programming Language :: Python :: 3.11
License-File: LICENSE
Requires-Dist: beautifulsoup4 ==4.12.3
Requires-Dist: httpx ==0.27.0
Requires-Dist: pypandoc ==1.13
Requires-Dist: rich ==13.7.1
